yourware_mcp/__init__.py
yourware_mcp/app.py
yourware_mcp/cli.py
yourware_mcp/client.py
yourware_mcp/credentials.py
yourware_mcp/log.py
yourware_mcp/utils.py
yourware_mcp-1.0.2.dist-info/METADATA
yourware_mcp-1.0.2.dist-info/WHEEL
yourware_mcp-1.0.2.dist-info/entry_points.txt
yourware_mcp-1.0.2.dist-info/licenses/LICENSE
yourware_mcp-1.0.2.dist-info/RECORD
